[
  {
    "assetId": "CoalRock",
    "layerId": "layer_0",
    "position": {
      "x": 190.9961487917014,
      "y": 2.2471796860071644,
      "z": 89.40301728570017
    },
    "rotation": {
      "x": 0,
      "y": -1.832595714594046,
      "z": 0
    },
    "scale": {
      "x": 1,
      "y": 1,
      "z": 1
    }
  },
  {
    "assetId": "CoalRock",
    "layerId": "layer_0",
    "position": {
      "x": 190.5,
      "y": 2.0293564037384666,
      "z": 92.5
    },
    "rotation": {
      "x": 0,
      "y": 0,
      "z": 0
    },
    "scale": {
      "x": 1,
      "y": 1,
      "z": 1
    }
  },
  {
    "assetId": "CoalRock",
    "layerId": "layer_0",
    "position": {
      "x": 188.5,
      "y": 3.0006182098527874,
      "z": 90.5
    },
    "rotation": {
      "x": 0,
      "y": 0,
      "z": 0
    },
    "scale": {
      "x": 1,
      "y": 1,
      "z": 1
    }
  },
  {
    "assetId": "willow tree",
    "layerId": "layer_0",
    "position": {
      "x": 162,
      "y": -0.6279083286612543,
      "z": 83
    },
    "rotation": {
      "x": 0,
      "y": 0,
      "z": 0
    },
    "scale": {
      "x": 1,
      "y": 1,
      "z": 1
    }
  },
  {
    "assetId": "stree autumn",
    "layerId": "layer_0",
    "position": {
      "x": 175,
      "y": 1.7095329579680687,
      "z": 91
    },
    "rotation": {
      "x": 0,
      "y": 0,
      "z": 0
    },
    "scale": {
      "x": 1,
      "y": 1,
      "z": 1
    }
  },
  {
    "assetId": "stree autumn",
    "layerId": "layer_0",
    "position": {
      "x": 178,
      "y": 3.334621695969737,
      "z": 88
    },
    "rotation": {
      "x": 0,
      "y": 0,
      "z": 0
    },
    "scale": {
      "x": 1,
      "y": 1,
      "z": 1
    }
  },
  {
    "assetId": "stree autumn",
    "layerId": "layer_0",
    "position": {
      "x": 175,
      "y": 1.5946463145424903,
      "z": 87
    },
    "rotation": {
      "x": 0,
      "y": 0,
      "z": 0
    },
    "scale": {
      "x": 1,
      "y": 1,
      "z": 1
    }
  },
  {
    "assetId": "stree autumn",
    "layerId": "layer_0",
    "position": {
      "x": 176,
      "y": 1.234323490415445,
      "z": 95
    },
    "rotation": {
      "x": 0,
      "y": 0,
      "z": 0
    },
    "scale": {
      "x": 1,
      "y": 1,
      "z": 1
    }
  },
  {
    "assetId": "stree autumn",
    "layerId": "layer_0",
    "position": {
      "x": 176,
      "y": 1.234404781726191,
      "z": 93
    },
    "rotation": {
      "x": 0,
      "y": 0,
      "z": 0
    },
    "scale": {
      "x": 1,
      "y": 1,
      "z": 1
    }
  },
  {
    "assetId": "stree autumn",
    "layerId": "layer_0",
    "position": {
      "x": 191,
      "y": 0.8199256082988268,
      "z": 95
    },
    "rotation": {
      "x": 0,
      "y": 0,
      "z": 0
    },
    "scale": {
      "x": 1,
      "y": 1,
      "z": 1
    }
  },
  {
    "assetId": "stree autumn",
    "layerId": "layer_0",
    "position": {
      "x": 189,
      "y": 1.4506323017986895,
      "z": 95
    },
    "rotation": {
      "x": 0,
      "y": 0,
      "z": 0
    },
    "scale": {
      "x": 1,
      "y": 1,
      "z": 1
    }
  },
  {
    "assetId": "DeadTreeLam",
    "layerId": "layer_0",
    "position": {
      "x": 183.08956829284273,
      "y": 3.4358931359857525,
      "z": 88.86504808299884
    },
    "rotation": {
      "x": 0.26179938779914935,
      "y": -0.7853981633974482,
      "z": 0
    },
    "scale": {
      "x": 1,
      "y": 1,
      "z": 1
    }
  },
  {
    "assetId": "DeadTreeLam",
    "layerId": "layer_0",
    "position": {
      "x": 188,
      "y": 3.2975096153792496,
      "z": 90
    },
    "rotation": {
      "x": 0,
      "y": 0.7853981633974483,
      "z": 0
    },
    "scale": {
      "x": 1,
      "y": 1,
      "z": 1
    }
  },
  {
    "assetId": "DeadTreeLam",
    "layerId": "layer_0",
    "position": {
      "x": 186,
      "y": 2.318931704032637,
      "z": 92
    },
    "rotation": {
      "x": 0.5235987755982987,
      "y": 1.308996938995747,
      "z": 0
    },
    "scale": {
      "x": 1,
      "y": 1,
      "z": 1
    }
  },
  {
    "assetId": "DeadTreeLam",
    "layerId": "layer_0",
    "position": {
      "x": 179.16411354009568,
      "y": 2.3722391706873256,
      "z": 92.43408220339515
    },
    "rotation": {
      "x": -0.5235987755982978,
      "y": -1.0471975511965954,
      "z": 0
    },
    "scale": {
      "x": 1,
      "y": 1,
      "z": 1
    }
  },
  {
    "assetId": "sTree 2",
    "layerId": "layer_0",
    "position": {
      "x": 162,
      "y": 0,
      "z": 87
    },
    "rotation": {
      "x": 0,
      "y": 0,
      "z": 0
    },
    "scale": {
      "x": 1,
      "y": 1,
      "z": 1
    }
  },
  {
    "assetId": "sTree 2",
    "layerId": "layer_0",
    "position": {
      "x": 165,
      "y": 0,
      "z": 88
    },
    "rotation": {
      "x": 0,
      "y": 0,
      "z": 0
    },
    "scale": {
      "x": 1,
      "y": 1,
      "z": 1
    }
  },
  {
    "assetId": "sTree 2",
    "layerId": "layer_0",
    "position": {
      "x": 165,
      "y": 0,
      "z": 92
    },
    "rotation": {
      "x": 0,
      "y": 0,
      "z": 0
    },
    "scale": {
      "x": 1,
      "y": 1,
      "z": 1
    }
  },
  {
    "assetId": "sTree 2",
    "layerId": "layer_0",
    "position": {
      "x": 167,
      "y": 0,
      "z": 90
    },
    "rotation": {
      "x": 0,
      "y": 0,
      "z": 0
    },
    "scale": {
      "x": 1,
      "y": 1,
      "z": 1
    }
  },
  {
    "assetId": "stree 3",
    "layerId": "layer_0",
    "position": {
      "x": 167,
      "y": 0,
      "z": 93
    },
    "rotation": {
      "x": 0,
      "y": 0,
      "z": 0
    },
    "scale": {
      "x": 1,
      "y": 1,
      "z": 1
    }
  },
  {
    "assetId": "stree 3",
    "layerId": "layer_0",
    "position": {
      "x": 165,
      "y": 0,
      "z": 95
    },
    "rotation": {
      "x": 0,
      "y": 0,
      "z": 0
    },
    "scale": {
      "x": 1,
      "y": 1,
      "z": 1
    }
  },
  {
    "assetId": "stree 3",
    "layerId": "layer_0",
    "position": {
      "x": 160,
      "y": 0,
      "z": 88
    },
    "rotation": {
      "x": 0,
      "y": 0,
      "z": 0
    },
    "scale": {
      "x": 1,
      "y": 1,
      "z": 1
    }
  },
  {
    "assetId": "sTree 2",
    "layerId": "layer_0",
    "position": {
      "x": 162,
      "y": 0,
      "z": 91
    },
    "rotation": {
      "x": 0,
      "y": 0,
      "z": 0
    },
    "scale": {
      "x": 1,
      "y": 1,
      "z": 1
    }
  },
  {
    "assetId": "sTree 2",
    "layerId": "layer_0",
    "position": {
      "x": 170,
      "y": 0.21845687892559695,
      "z": 90
    },
    "rotation": {
      "x": 0,
      "y": 0,
      "z": 0
    },
    "scale": {
      "x": 1,
      "y": 1,
      "z": 1
    }
  },
  {
    "assetId": "sTree 2",
    "layerId": "layer_0",
    "position": {
      "x": 172,
      "y": 0.351691901305621,
      "z": 94
    },
    "rotation": {
      "x": 0,
      "y": 0,
      "z": 0
    },
    "scale": {
      "x": 1,
      "y": 1,
      "z": 1
    }
  },
  {
    "assetId": "sTree 2",
    "layerId": "layer_0",
    "position": {
      "x": 170,
      "y": 0.09455925148084532,
      "z": 86
    },
    "rotation": {
      "x": 0,
      "y": 0,
      "z": 0
    },
    "scale": {
      "x": 1,
      "y": 1,
      "z": 1
    }
  },
  {
    "assetId": "sTree 2",
    "layerId": "layer_0",
    "position": {
      "x": 167,
      "y": -0.08629739497218836,
      "z": 85
    },
    "rotation": {
      "x": 0,
      "y": 0,
      "z": 0
    },
    "scale": {
      "x": 1,
      "y": 1,
      "z": 1
    }
  },
  {
    "assetId": "bush2",
    "layerId": "layer_0",
    "position": {
      "x": 189.5,
      "y": 3.4759927686105474,
      "z": 89.5
    },
    "rotation": {
      "x": 0,
      "y": 0,
      "z": 0
    },
    "scale": {
      "x": 1,
      "y": 1,
      "z": 1
    }
  },
  {
    "assetId": "bush2",
    "layerId": "layer_0",
    "position": {
      "x": 190.5,
      "y": 2.873005552502452,
      "z": 90.5
    },
    "rotation": {
      "x": 0,
      "y": 0,
      "z": 0
    },
    "scale": {
      "x": 1,
      "y": 1,
      "z": 1
    }
  },
  {
    "assetId": "bush2",
    "layerId": "layer_0",
    "position": {
      "x": 187.5,
      "y": 4.031364368628553,
      "z": 88.5
    },
    "rotation": {
      "x": 0,
      "y": 0,
      "z": 0
    },
    "scale": {
      "x": 1,
      "y": 1,
      "z": 1
    }
  },
  {
    "assetId": "bush2",
    "layerId": "layer_0",
    "position": {
      "x": 188.5,
      "y": 3.908620108630764,
      "z": 88.5
    },
    "rotation": {
      "x": 0,
      "y": 0,
      "z": 0
    },
    "scale": {
      "x": 1,
      "y": 1,
      "z": 1
    }
  },
  {
    "assetId": "bush2",
    "layerId": "layer_0",
    "position": {
      "x": 182.5,
      "y": 3.9255634369719807,
      "z": 88.5
    },
    "rotation": {
      "x": 0,
      "y": 0,
      "z": 0
    },
    "scale": {
      "x": 1,
      "y": 1,
      "z": 1
    }
  },
  {
    "assetId": "bush2",
    "layerId": "layer_0",
    "position": {
      "x": 179.5,
      "y": 3.1423620551431366,
      "z": 91.5
    },
    "rotation": {
      "x": 0,
      "y": 0,
      "z": 0
    },
    "scale": {
      "x": 1,
      "y": 1,
      "z": 1
    }
  },
  {
    "assetId": "bush2",
    "layerId": "layer_0",
    "position": {
      "x": 187.5,
      "y": 1.6161522552498897,
      "z": 94.5
    },
    "rotation": {
      "x": 0.25268025514207865,
      "y": 0.06923949433189555,
      "z": 0.27059741512222635
    },
    "scale": {
      "x": 1,
      "y": 1,
      "z": 1
    }
  }
]
