[
  {
    "assetId": "castleTruedoor",
    "layerId": "layer_0",
    "position": {
      "x": 245.0717358276733,
      "y": 3.9463642309556235e-7,
      "z": 219.55108627220523
    },
    "rotation": {
      "x": -1.1102230246251553e-16,
      "y": -1.5707963267948963,
      "z": 0
    },
    "scale": {
      "x": 1.4499999999999997,
      "y": 2.0499999999999994,
      "z": 1.4499999999999997
    }
  },
  {
    "assetId": "limestone slab",
    "layerId": "layer_0",
    "position": {
      "x": 228.77228233280493,
      "y": 2.647074738415868,
      "z": 221
    },
    "rotation": {
      "x": 0,
      "y": 0,
      "z": 0
    },
    "scale": {
      "x": 0.6999999999999998,
      "y": 1.15,
      "z": 0.5499999999999999
    }
  },
  {
    "assetId": "limestone wall",
    "layerId": "layer_0",
    "position": {
      "x": 226.9543922935472,
      "y": -0.0899504134481522,
      "z": 218
    },
    "rotation": {
      "x": 0,
      "y": 1.5707963267948966,
      "z": 0
    },
    "scale": {
      "x": 1,
      "y": 1,
      "z": 1
    }
  },
  {
    "assetId": "limestone wall",
    "layerId": "layer_0",
    "position": {
      "x": 228,
      "y": -0.06511305472322355,
      "z": 217
    },
    "rotation": {
      "x": 0,
      "y": 3.141592653589793,
      "z": 0
    },
    "scale": {
      "x": 1,
      "y": 1,
      "z": 1
    }
  },
  {
    "assetId": "limestone wall",
    "layerId": "layer_0",
    "position": {
      "x": 230,
      "y": -0.06511305472322355,
      "z": 217
    },
    "rotation": {
      "x": 0,
      "y": 3.141592653589793,
      "z": 0
    },
    "scale": {
      "x": 1,
      "y": 1,
      "z": 1
    }
  },
  {
    "assetId": "limestone wall",
    "layerId": "layer_0",
    "position": {
      "x": 227.5,
      "y": -0.0899504134481522,
      "z": 220
    },
    "rotation": {
      "x": 0,
      "y": 2.0943951023931957,
      "z": 0
    },
    "scale": {
      "x": 1.15,
      "y": 0.9999999999999999,
      "z": 0.9999999999999999
    }
  },
  {
    "assetId": "limestone wall",
    "layerId": "layer_0",
    "position": {
      "x": 231,
      "y": -0.08995041344815131,
      "z": 218
    },
    "rotation": {
      "x": 0,
      "y": -1.570796326794897,
      "z": 0
    },
    "scale": {
      "x": 1,
      "y": 1,
      "z": 1
    }
  },
  {
    "assetId": "limestone wall",
    "layerId": "layer_0",
    "position": {
      "x": 231,
      "y": -0.08995041344815131,
      "z": 220
    },
    "rotation": {
      "x": 0,
      "y": 1.5707963267948961,
      "z": 0
    },
    "scale": {
      "x": 1,
      "y": 1,
      "z": 1
    }
  },
  {
    "assetId": "limestone doorframe",
    "layerId": "layer_0",
    "position": {
      "x": 229.5,
      "y": -0.0899504134481522,
      "z": 221
    },
    "rotation": {
      "x": 0,
      "y": 0,
      "z": 0
    },
    "scale": {
      "x": 1.4499999999999997,
      "y": 0.9999999999999999,
      "z": 0.9999999999999999
    }
  },
  {
    "assetId": "basicTruedoor",
    "layerId": "layer_0",
    "position": {
      "x": 229.5,
      "y": -0.08995041344815131,
      "z": 221
    },
    "rotation": {
      "x": 6.162975822039155e-33,
      "y": 1.5707963267948963,
      "z": 1.1102230246251568e-16
    },
    "scale": {
      "x": 1,
      "y": 0.9999999999999999,
      "z": 1
    }
  },
  {
    "assetId": "limestone slab",
    "layerId": "layer_0",
    "position": {
      "x": 230.16343157243813,
      "y": 2.647074738415868,
      "z": 221
    },
    "rotation": {
      "x": 0,
      "y": 0,
      "z": 0
    },
    "scale": {
      "x": 0.6999999999999998,
      "y": 1.15,
      "z": 0.5499999999999999
    }
  },
  {
    "assetId": "limestone slab",
    "layerId": "layer_0",
    "position": {
      "x": 230.98752947128014,
      "y": 2.650049586551848,
      "z": 220.43645042759255
    },
    "rotation": {
      "x": 0,
      "y": 1.5707963267948966,
      "z": 0
    },
    "scale": {
      "x": 0.6999999999999998,
      "y": 1.15,
      "z": 0.5499999999999999
    }
  },
  {
    "assetId": "limestone slab",
    "layerId": "layer_0",
    "position": {
      "x": 230.98752947128014,
      "y": 2.650049586551848,
      "z": 219.0364504443965
    },
    "rotation": {
      "x": 0,
      "y": 1.5707963267948966,
      "z": 0
    },
    "scale": {
      "x": 0.6999999999999998,
      "y": 1.15,
      "z": 0.5499999999999999
    }
  },
  {
    "assetId": "limestone slab",
    "layerId": "layer_0",
    "position": {
      "x": 230.98752947128014,
      "y": 2.650049586551848,
      "z": 217.63645046120047
    },
    "rotation": {
      "x": 0,
      "y": 1.5707963267948966,
      "z": 0
    },
    "scale": {
      "x": 0.6999999999999998,
      "y": 1.15,
      "z": 0.5499999999999999
    }
  },
  {
    "assetId": "limestone slab",
    "layerId": "layer_0",
    "position": {
      "x": 230.22159805503287,
      "y": 2.6474003856448842,
      "z": 217
    },
    "rotation": {
      "x": 0,
      "y": 3.141592653589793,
      "z": 0
    },
    "scale": {
      "x": 0.6999999999999998,
      "y": 1.15,
      "z": 0.5499999999999999
    }
  },
  {
    "assetId": "limestone slab",
    "layerId": "layer_0",
    "position": {
      "x": 228.82488148567,
      "y": 2.6474003856448842,
      "z": 217
    },
    "rotation": {
      "x": 0,
      "y": 3.141592653589793,
      "z": 0
    },
    "scale": {
      "x": 0.6999999999999998,
      "y": 1.15,
      "z": 0.5499999999999999
    }
  },
  {
    "assetId": "limestone slab",
    "layerId": "layer_0",
    "position": {
      "x": 227.57913059108594,
      "y": 2.6474003856448842,
      "z": 217
    },
    "rotation": {
      "x": 0,
      "y": 3.141592653589793,
      "z": 0
    },
    "scale": {
      "x": 0.5499999999999998,
      "y": 1.15,
      "z": 0.5499999999999999
    }
  },
  {
    "assetId": "limestone slab",
    "layerId": "layer_0",
    "position": {
      "x": 226.95160144259205,
      "y": 2.650049586551848,
      "z": 217.9996495930952
    },
    "rotation": {
      "x": 0,
      "y": 1.5707963267948966,
      "z": 0
    },
    "scale": {
      "x": 0.9999999999999999,
      "y": 1.15,
      "z": 0.5499999999999999
    }
  },
  {
    "assetId": "limestone slab",
    "layerId": "layer_0",
    "position": {
      "x": 227.81007218734322,
      "y": 2.6532498886758713,
      "z": 220.47496020973566
    },
    "rotation": {
      "x": 0,
      "y": 2.0943951023931957,
      "z": 0
    },
    "scale": {
      "x": 0.5499999999999998,
      "y": 1.15,
      "z": 0.5499999999999999
    }
  },
  {
    "assetId": "limestone slab",
    "layerId": "layer_0",
    "position": {
      "x": 227.26331769276973,
      "y": 2.6532498886758713,
      "z": 219.5205067780388
    },
    "rotation": {
      "x": 0,
      "y": 2.0943951023931957,
      "z": 0
    },
    "scale": {
      "x": 0.5499999999999998,
      "y": 1.15,
      "z": 0.5499999999999999
    }
  },
  {
    "assetId": "limestone wall",
    "layerId": "layer_0",
    "position": {
      "x": 246.07173564763744,
      "y": 3.94636415990135e-7,
      "z": 220.99999976445832
    },
    "rotation": {
      "x": -9.937409426356771e-33,
      "y": -3.885780586188051e-16,
      "z": -3.925231146709439e-17
    },
    "scale": {
      "x": 1,
      "y": 1,
      "z": 1
    }
  },
  {
    "assetId": "limestone wall",
    "layerId": "layer_0",
    "position": {
      "x": 248.07173532399787,
      "y": 3.9463641821058104e-7,
      "z": 220.9999997896027
    },
    "rotation": {
      "x": -9.937409426356771e-33,
      "y": -3.885780586188051e-16,
      "z": -3.925231146709439e-17
    },
    "scale": {
      "x": 1,
      "y": 1,
      "z": 1
    }
  },
  {
    "assetId": "limestone wall",
    "layerId": "layer_0",
    "position": {
      "x": 249.05318051306133,
      "y": 3.946364111051537e-7,
      "z": 219.99999996399475
    },
    "rotation": {
      "x": 1.1102230246251553e-16,
      "y": 1.5707963267948961,
      "z": -3.697785493223498e-32
    },
    "scale": {
      "x": 1,
      "y": 1,
      "z": 1
    }
  },
  {
    "assetId": "limestone wall",
    "layerId": "layer_0",
    "position": {
      "x": 249.05318053820577,
      "y": 3.946364106610645e-7,
      "z": 218.00000028763432
    },
    "rotation": {
      "x": 1.1102230246251553e-16,
      "y": 1.5707963267948961,
      "z": -3.697785493223498e-32
    },
    "scale": {
      "x": 1,
      "y": 1,
      "z": 1
    }
  },
  {
    "assetId": "limestone wall",
    "layerId": "layer_0",
    "position": {
      "x": 248.07173537428676,
      "y": 3.9463641821058104e-7,
      "z": 217.0000004368819
    },
    "rotation": {
      "x": 2.0832114416488326e-32,
      "y": 3.1415926535897922,
      "z": 3.92523114670944e-17
    },
    "scale": {
      "x": 1,
      "y": 1,
      "z": 1
    }
  },
  {
    "assetId": "limestone wall",
    "layerId": "layer_0",
    "position": {
      "x": 246.07173569792633,
      "y": 3.946364164342242e-7,
      "z": 217.00000041173743
    },
    "rotation": {
      "x": 2.0832114416488326e-32,
      "y": 3.1415926535897922,
      "z": 3.92523114670944e-17
    },
    "scale": {
      "x": 1,
      "y": 1,
      "z": 1
    }
  },
  {
    "assetId": "limestone doorframe",
    "layerId": "layer_0",
    "position": {
      "x": 245.07173582777108,
      "y": 3.946364213192055e-7,
      "z": 219.54330954996442
    },
    "rotation": {
      "x": -1.1102230246251553e-16,
      "y": -1.5707963267948963,
      "z": 0
    },
    "scale": {
      "x": 1.4499999999999997,
      "y": 1,
      "z": 1
    }
  },
  {
    "assetId": "limestone wall",
    "layerId": "layer_0",
    "position": {
      "x": 245.07173585283482,
      "y": 3.946364204310271e-7,
      "z": 217.54972693417892
    },
    "rotation": {
      "x": -1.1102230246251544e-16,
      "y": -1.5707963267948977,
      "z": 7.395570986446996e-32
    },
    "scale": {
      "x": 0.5499999999999999,
      "y": 1,
      "z": 1
    }
  },
  {
    "assetId": "limestone stairs",
    "layerId": "layer_0",
    "position": {
      "x": 248.53344313029393,
      "y": 3.946364155460458e-7,
      "z": 219.50257213529457
    },
    "rotation": {
      "x": 1.3217493523837047e-34,
      "y": -3.141592653589793,
      "z": 3.925231146709439e-17
    },
    "scale": {
      "x": 1,
      "y": 1,
      "z": 1
    },
    "verticalLinks": [
      {
        "from": {
          "x": 248.5,
          "z": 220.5,
          "floor": 0,
          "y": 0
        },
        "to": {
          "x": 248.5,
          "z": 220.5,
          "floor": 1,
          "y": 2.720000101203174
        },
        "fromAction": "Climb-up"
      },
      {
        "from": {
          "x": 248.5,
          "z": 220.5,
          "floor": 1,
          "y": 2.720000101203174
        },
        "to": {
          "x": 248.5,
          "z": 220.5,
          "floor": 0,
          "y": 0
        },
        "fromAction": "Climb-down"
      }
    ]
  },
  {
    "assetId": "limestone wall",
    "layerId": "layer_0",
    "position": {
      "x": 249.05318050556713,
      "y": 2.7432004008243536,
      "z": 220.59609175556685
    },
    "rotation": {
      "x": 1.1102230246251553e-16,
      "y": 1.5707963267948961,
      "z": -3.697785493223498e-32
    },
    "scale": {
      "x": 1.2999999999999998,
      "y": 1,
      "z": 1
    }
  },
  {
    "assetId": "limestone wall",
    "layerId": "layer_0",
    "position": {
      "x": 249.05318053630873,
      "y": 2.7432004008243576,
      "z": 218.15088771671572
    },
    "rotation": {
      "x": 1.1102230246251553e-16,
      "y": 1.5707963267948961,
      "z": -3.697785493223498e-32
    },
    "scale": {
      "x": 1.15,
      "y": 1,
      "z": 1
    }
  },
  {
    "assetId": "limestone wall",
    "layerId": "layer_0",
    "position": {
      "x": 245.07173581458466,
      "y": 2.7432004008243625,
      "z": 220.59216224120948
    },
    "rotation": {
      "x": 1.1102230246251562e-16,
      "y": 1.5707963267948961,
      "z": 1.1102230246251563e-16
    },
    "scale": {
      "x": 1.2999999999999998,
      "y": 1,
      "z": 1
    }
  },
  {
    "assetId": "limestone wall",
    "layerId": "layer_0",
    "position": {
      "x": 245.0717358452506,
      "y": 2.7455383331588137,
      "z": 218.15298503063573
    },
    "rotation": {
      "x": 1.1102230246251562e-16,
      "y": 1.5707963267948961,
      "z": 1.1102230246251563e-16
    },
    "scale": {
      "x": 1.15,
      "y": 1,
      "z": 1
    }
  },
  {
    "assetId": "limestone wall",
    "layerId": "layer_0",
    "position": {
      "x": 248.0717353742868,
      "y": 2.7200001298134024,
      "z": 217.0000004368819
    },
    "rotation": {
      "x": 2.0832114416488326e-32,
      "y": 3.1415926535897922,
      "z": 3.92523114670944e-17
    },
    "scale": {
      "x": 0.9999999999999999,
      "y": 1,
      "z": 1
    }
  },
  {
    "assetId": "limestone wall",
    "layerId": "layer_0",
    "position": {
      "x": 246.07173569792633,
      "y": 2.7432004008243553,
      "z": 217.00000041173743
    },
    "rotation": {
      "x": 2.0832114416488326e-32,
      "y": 3.1415926535897922,
      "z": 3.92523114670944e-17
    },
    "scale": {
      "x": 0.9999999999999999,
      "y": 1,
      "z": 1
    }
  },
  {
    "assetId": "limestone slab",
    "layerId": "layer_0",
    "position": {
      "x": 245.78200132715602,
      "y": 5.486400407012299,
      "z": 217.0000004080949
    },
    "rotation": {
      "x": 7.850462293418867e-17,
      "y": -2.2204460492503146e-16,
      "z": -3.92523114670944e-17
    },
    "scale": {
      "x": 0.6999999999999998,
      "y": 1.15,
      "z": 0.5499999999999999
    }
  },
  {
    "assetId": "limestone slab",
    "layerId": "layer_0",
    "position": {
      "x": 247.18200108380435,
      "y": 5.4864004070122965,
      "z": 217.00000042569602
    },
    "rotation": {
      "x": 7.850462293418867e-17,
      "y": -2.2204460492503146e-16,
      "z": -3.92523114670944e-17
    },
    "scale": {
      "x": 0.6999999999999998,
      "y": 1.15,
      "z": 0.5499999999999999
    }
  },
  {
    "assetId": "limestone slab",
    "layerId": "layer_0",
    "position": {
      "x": 248.4318111624498,
      "y": 5.486400407012303,
      "z": 217.00000044140884
    },
    "rotation": {
      "x": 7.850462293418867e-17,
      "y": -2.2204460492503146e-16,
      "z": -3.92523114670944e-17
    },
    "scale": {
      "x": 0.5499999999999998,
      "y": 1.15,
      "z": 0.5499999999999999
    }
  },
  {
    "assetId": "limestone slab",
    "layerId": "layer_0",
    "position": {
      "x": 249.06025758003958,
      "y": 5.48640040701231,
      "z": 217.7267165632062
    },
    "rotation": {
      "x": 1.1102230246251548e-16,
      "y": 1.5707963267948966,
      "z": -6.162975822039163e-33
    },
    "scale": {
      "x": 0.6999999999999998,
      "y": 1.15,
      "z": 0.5499999999999999
    }
  },
  {
    "assetId": "limestone slab",
    "layerId": "layer_0",
    "position": {
      "x": 249.06025756243844,
      "y": 5.486400407012306,
      "z": 219.12671631985452
    },
    "rotation": {
      "x": 1.1102230246251548e-16,
      "y": 1.5707963267948966,
      "z": -6.162975822039163e-33
    },
    "scale": {
      "x": 0.6999999999999998,
      "y": 1.15,
      "z": 0.5499999999999999
    }
  },
  {
    "assetId": "limestone slab",
    "layerId": "layer_0",
    "position": {
      "x": 249.06025754673834,
      "y": 5.486400407012304,
      "z": 220.3755104292897
    },
    "rotation": {
      "x": 1.1102230246251548e-16,
      "y": 1.5707963267948966,
      "z": -6.162975822039163e-33
    },
    "scale": {
      "x": 0.5499999999999998,
      "y": 1.15,
      "z": 0.5499999999999999
    }
  },
  {
    "assetId": "limestone slab",
    "layerId": "layer_0",
    "position": {
      "x": 249.0602575328528,
      "y": 5.486400407012304,
      "z": 221.4799704141165
    },
    "rotation": {
      "x": 1.1102230246251548e-16,
      "y": 1.5707963267948966,
      "z": -6.162975822039163e-33
    },
    "scale": {
      "x": 0.5499999999999998,
      "y": 1.15,
      "z": 0.5499999999999999
    }
  },
  {
    "assetId": "limestone slab",
    "layerId": "layer_0",
    "position": {
      "x": 245.07173585078093,
      "y": 5.4887383393467575,
      "z": 217.7130983064056
    },
    "rotation": {
      "x": 1.1102230246251548e-16,
      "y": 1.5707963267948966,
      "z": -6.162975822039163e-33
    },
    "scale": {
      "x": 0.6999999999999998,
      "y": 1.15,
      "z": 0.5499999999999999
    }
  },
  {
    "assetId": "limestone slab",
    "layerId": "layer_0",
    "position": {
      "x": 245.07173583317982,
      "y": 5.488738339346761,
      "z": 219.1130980630539
    },
    "rotation": {
      "x": 1.1102230246251548e-16,
      "y": 1.5707963267948966,
      "z": -6.162975822039163e-33
    },
    "scale": {
      "x": 0.6999999999999998,
      "y": 1.15,
      "z": 0.5499999999999999
    }
  },
  {
    "assetId": "limestone slab",
    "layerId": "layer_0",
    "position": {
      "x": 245.0717358174797,
      "y": 5.488738339346762,
      "z": 220.36189217248915
    },
    "rotation": {
      "x": 1.1102230246251548e-16,
      "y": 1.5707963267948966,
      "z": -6.162975822039163e-33
    },
    "scale": {
      "x": 0.5499999999999998,
      "y": 1.15,
      "z": 0.5499999999999999
    }
  },
  {
    "assetId": "limestone slab",
    "layerId": "layer_0",
    "position": {
      "x": 245.0717358035942,
      "y": 5.488738339346762,
      "z": 221.46635215731592
    },
    "rotation": {
      "x": 1.1102230246251548e-16,
      "y": 1.5707963267948966,
      "z": -6.162975822039163e-33
    },
    "scale": {
      "x": 0.5499999999999998,
      "y": 1.15,
      "z": 0.5499999999999999
    }
  },
  {
    "assetId": "limestone wall",
    "layerId": "layer_0",
    "position": {
      "x": 248.06082606511023,
      "y": 3.946365829676779e-7,
      "z": 222.90984348896936
    },
    "rotation": {
      "x": -4.599554232854033e-33,
      "y": 3.1415926535897927,
      "z": -3.9252311467094385e-17
    },
    "scale": {
      "x": 1,
      "y": 1,
      "z": 1
    }
  },
  {
    "assetId": "limestone wall",
    "layerId": "layer_0",
    "position": {
      "x": 246.0608267123894,
      "y": 3.9463658518812395e-7,
      "z": 222.90984351411385
    },
    "rotation": {
      "x": -4.599554232854033e-33,
      "y": 3.1415926535897927,
      "z": -3.9252311467094385e-17
    },
    "scale": {
      "x": 1,
      "y": 1,
      "z": 1
    }
  },
  {
    "assetId": "limestone wall",
    "layerId": "layer_0",
    "position": {
      "x": 248.98109338559829,
      "y": 3.946365780826966e-7,
      "z": 223.8168859705887
    },
    "rotation": {
      "x": 1.110223024625154e-16,
      "y": -1.5707963267948977,
      "z": -4.314083075427413e-32
    },
    "scale": {
      "x": 1,
      "y": 1,
      "z": 1
    }
  },
  {
    "assetId": "limestone wall",
    "layerId": "layer_0",
    "position": {
      "x": 245.06123999468628,
      "y": -1.7763568394002505e-15,
      "z": 223.34198106707717
    },
    "rotation": {
      "x": -1.1102230246251531e-16,
      "y": 1.5707963267948952,
      "z": 8.011868568650911e-32
    },
    "scale": {
      "x": 0.5499999999999999,
      "y": 1,
      "z": 1
    }
  },
  {
    "assetId": "limestone stairs",
    "layerId": "layer_0",
    "position": {
      "x": 246.60808009911193,
      "y": 0,
      "z": 223.50179782230836
    },
    "rotation": {
      "x": -3.0814879110195774e-33,
      "y": 1.5707963267948963,
      "z": 3.92523114670944e-17
    },
    "scale": {
      "x": 1,
      "y": 1,
      "z": 1
    },
    "verticalLinks": [
      {
        "from": {
          "x": 246.5,
          "z": 224.5,
          "floor": 0,
          "y": 0.02331894929751771
        },
        "to": {
          "x": 246.5,
          "z": 224.5,
          "floor": 1,
          "y": 2.7200001012033423
        },
        "fromAction": "Climb-up"
      },
      {
        "from": {
          "x": 246.5,
          "z": 224.5,
          "floor": 1,
          "y": 2.7200001012033423
        },
        "to": {
          "x": 246.5,
          "z": 224.5,
          "floor": 0,
          "y": 0.02331894929751771
        },
        "fromAction": "Climb-down"
      }
    ]
  },
  {
    "assetId": "limestone wall",
    "layerId": "layer_0",
    "position": {
      "x": 245.06082704110693,
      "y": 2.7432004008245205,
      "z": 223.19424738383756
    },
    "rotation": {
      "x": 1.110223024625154e-16,
      "y": -1.5707963267948977,
      "z": -4.314083075427413e-32
    },
    "scale": {
      "x": 1.2999999999999998,
      "y": 1,
      "z": 1
    }
  },
  {
    "assetId": "limestone wall",
    "layerId": "layer_0",
    "position": {
      "x": 249.03725170402194,
      "y": 2.7432004008245294,
      "z": 223.2028282522852
    },
    "rotation": {
      "x": 1.1102230246251548e-16,
      "y": -1.5707963267948977,
      "z": 1.1102230246251563e-16
    },
    "scale": {
      "x": 1.2999999999999998,
      "y": 1,
      "z": 1
    }
  },
  {
    "assetId": "limestone slab",
    "layerId": "layer_0",
    "position": {
      "x": 245.07230466531382,
      "y": 5.486400407012471,
      "z": 223.44137556577013
    },
    "rotation": {
      "x": 1.1102230246251536e-16,
      "y": -1.5707963267948972,
      "z": -6.16297582203916e-33
    },
    "scale": {
      "x": 0.5499999999999998,
      "y": 1.15,
      "z": 0.5499999999999999
    }
  },
  {
    "assetId": "limestone slab",
    "layerId": "layer_0",
    "position": {
      "x": 245.0723046514283,
      "y": 5.486400407012471,
      "z": 222.33691575966688
    },
    "rotation": {
      "x": 1.1102230246251536e-16,
      "y": -1.5707963267948972,
      "z": -6.16297582203916e-33
    },
    "scale": {
      "x": 0.5499999999999998,
      "y": 1.15,
      "z": 0.5499999999999999
    }
  },
  {
    "assetId": "limestone slab",
    "layerId": "layer_0",
    "position": {
      "x": 249.06082574949312,
      "y": 5.488738339346929,
      "z": 223.4549937200779
    },
    "rotation": {
      "x": 1.1102230246251536e-16,
      "y": -1.5707963267948972,
      "z": -6.16297582203916e-33
    },
    "scale": {
      "x": 0.5499999999999998,
      "y": 1.15,
      "z": 0.5499999999999999
    }
  },
  {
    "assetId": "limestone slab",
    "layerId": "layer_0",
    "position": {
      "x": 249.06082573560755,
      "y": 5.488738339346929,
      "z": 222.3505339139746
    },
    "rotation": {
      "x": 1.1102230246251536e-16,
      "y": -1.5707963267948972,
      "z": -6.16297582203916e-33
    },
    "scale": {
      "x": 0.5499999999999998,
      "y": 1.15,
      "z": 0.5499999999999999
    }
  },
  {
    "assetId": "stone wall",
    "layerId": "layer_0",
    "position": {
      "x": 224.02346005465404,
      "y": -0.0878990752440544,
      "z": 218.397050112134
    },
    "rotation": {
      "x": 0,
      "y": 1.5707963267948961,
      "z": 0
    },
    "scale": {
      "x": 1.4499999999999997,
      "y": 0.85,
      "z": 1
    }
  },
  {
    "assetId": "roof corner",
    "layerId": "layer_0",
    "position": {
      "x": 224.13172462183252,
      "y": 2.037387430241415,
      "z": 219.40455706238015
    },
    "rotation": {
      "x": 0,
      "y": -1.1102230246251573e-16,
      "z": 0
    },
    "scale": {
      "x": 1,
      "y": 1,
      "z": 1
    }
  },
  {
    "assetId": "roof corner",
    "layerId": "layer_0",
    "position": {
      "x": 224.1230701481898,
      "y": 2.037387430241415,
      "z": 216.98083919019624
    },
    "rotation": {
      "x": 0,
      "y": 1.5707963267948961,
      "z": 0
    },
    "scale": {
      "x": 1,
      "y": 1,
      "z": 1
    }
  },
  {
    "assetId": "tile roofing",
    "layerId": "layer_0",
    "position": {
      "x": 224.64274019963437,
      "y": 2.0378349714926753,
      "z": 218.1426617648561
    },
    "rotation": {
      "x": 0,
      "y": 1.5707963267948961,
      "z": 0
    },
    "scale": {
      "x": 1,
      "y": 1,
      "z": 1
    }
  },
  {
    "assetId": "MinecartTrackStraight",
    "layerId": "layer_0",
    "position": {
      "x": 255.5,
      "y": 0,
      "z": 215.5
    },
    "rotation": {
      "x": 0,
      "y": 1.5707963267948966,
      "z": 0
    },
    "scale": {
      "x": 1,
      "y": 1,
      "z": 1
    }
  },
  {
    "assetId": "MinecartTrackStraight",
    "layerId": "layer_0",
    "position": {
      "x": 254.5,
      "y": 0,
      "z": 215.5
    },
    "rotation": {
      "x": 0,
      "y": 1.5707963267948966,
      "z": 0
    },
    "scale": {
      "x": 1,
      "y": 1,
      "z": 1
    }
  },
  {
    "assetId": "MinecartTrackStraight",
    "layerId": "layer_0",
    "position": {
      "x": 253.5,
      "y": 0,
      "z": 215.5
    },
    "rotation": {
      "x": 0,
      "y": 1.5707963267948966,
      "z": 0
    },
    "scale": {
      "x": 1,
      "y": 1,
      "z": 1
    }
  },
  {
    "assetId": "MinecartTrackStraight",
    "layerId": "layer_0",
    "position": {
      "x": 252.5,
      "y": 0.007167839655008177,
      "z": 215.5
    },
    "rotation": {
      "x": 0,
      "y": 1.5707963267948966,
      "z": 0
    },
    "scale": {
      "x": 1,
      "y": 1,
      "z": 1
    }
  },
  {
    "assetId": "MinecartTrackStraight",
    "layerId": "layer_0",
    "position": {
      "x": 251.5,
      "y": 0.032500600767311844,
      "z": 215.5
    },
    "rotation": {
      "x": 0,
      "y": 1.5707963267948966,
      "z": 0
    },
    "scale": {
      "x": 1,
      "y": 1,
      "z": 1
    }
  },
  {
    "assetId": "MinecartTrackStraight",
    "layerId": "layer_0",
    "position": {
      "x": 250.5,
      "y": 0.07827807205156605,
      "z": 215.5
    },
    "rotation": {
      "x": 0.08726646259971642,
      "y": 1.5707963267948966,
      "z": -1.3930798702701364e-17
    },
    "scale": {
      "x": 1,
      "y": 1,
      "z": 1
    }
  },
  {
    "assetId": "MinecartTrackStraight",
    "layerId": "layer_0",
    "position": {
      "x": 249.5,
      "y": 0.15640163282448893,
      "z": 215.5
    },
    "rotation": {
      "x": 0.03490658503988658,
      "y": 1.5707963267948966,
      "z": -6.943123467126486e-18
    },
    "scale": {
      "x": 1,
      "y": 1,
      "z": 1
    }
  },
  {
    "assetId": "MinecartTrackStraight",
    "layerId": "layer_0",
    "position": {
      "x": 248.5,
      "y": 0.18318649700733586,
      "z": 215.5
    },
    "rotation": {
      "x": 0.0349065850398866,
      "y": 1.5707963267948966,
      "z": -3.818717906919566e-17
    },
    "scale": {
      "x": 1,
      "y": 1,
      "z": 1
    }
  },
  {
    "assetId": "MinecartTrackStraight",
    "layerId": "layer_0",
    "position": {
      "x": 247.5,
      "y": 0.20131005778025873,
      "z": 215.5
    },
    "rotation": {
      "x": 1.2266347333466993e-17,
      "y": 1.5707963267948963,
      "z": 4.906538933386795e-18
    },
    "scale": {
      "x": 1,
      "y": 1,
      "z": 1
    }
  },
  {
    "assetId": "MinecartTrackStraight",
    "layerId": "layer_0",
    "position": {
      "x": 246.5027182568744,
      "y": 0.22285043291024573,
      "z": 215.5
    },
    "rotation": {
      "x": 0.03490658503988664,
      "y": 1.5707963267948966,
      "z": 0
    },
    "scale": {
      "x": 1,
      "y": 1,
      "z": 1
    }
  },
  {
    "assetId": "MinecartTrackStraight",
    "layerId": "layer_0",
    "position": {
      "x": 245.5,
      "y": 0.24853097592610526,
      "z": 215.5
    },
    "rotation": {
      "x": -0.017453292519943295,
      "y": 1.5707963267948968,
      "z": -5.0314643967308056e-17
    },
    "scale": {
      "x": 1,
      "y": 1,
      "z": 1
    }
  },
  {
    "assetId": "MinecartTrackStraight",
    "layerId": "layer_0",
    "position": {
      "x": 244.5,
      "y": 0.15485271216748156,
      "z": 215.5
    },
    "rotation": {
      "x": -0.06981317007977318,
      "y": 1.5707963267948968,
      "z": -6.955837975616632e-17
    },
    "scale": {
      "x": 1,
      "y": 1,
      "z": 1
    }
  },
  {
    "assetId": "MinecartTrackStraight",
    "layerId": "layer_0",
    "position": {
      "x": 243.5,
      "y": 0.0797652421520165,
      "z": 215.5
    },
    "rotation": {
      "x": -0.06981317007977318,
      "y": 1.5707963267948968,
      "z": -6.955837975616632e-17
    },
    "scale": {
      "x": 1,
      "y": 1,
      "z": 1
    }
  },
  {
    "assetId": "MinecartTrackStraight",
    "layerId": "layer_0",
    "position": {
      "x": 242.5,
      "y": 0.02,
      "z": 215.5
    },
    "rotation": {
      "x": -0.052359877559829876,
      "y": 1.5707963267948966,
      "z": 1.0422624700779381e-17
    },
    "scale": {
      "x": 1,
      "y": 1,
      "z": 1
    }
  },
  {
    "assetId": "MinecartTrackStraight",
    "layerId": "layer_0",
    "position": {
      "x": 241.5,
      "y": 0.04,
      "z": 215.5
    },
    "rotation": {
      "x": 0,
      "y": 1.5707963267948966,
      "z": 0
    },
    "scale": {
      "x": 1,
      "y": 1,
      "z": 1
    }
  },
  {
    "assetId": "MinecartTrackStraight",
    "layerId": "layer_0",
    "position": {
      "x": 240.5,
      "y": 0.04,
      "z": 215.5
    },
    "rotation": {
      "x": 0,
      "y": 1.5707963267948966,
      "z": 0
    },
    "scale": {
      "x": 1,
      "y": 1,
      "z": 1
    }
  },
  {
    "assetId": "MinecartTrackStraight",
    "layerId": "layer_0",
    "position": {
      "x": 239.5,
      "y": 0.04,
      "z": 215.5
    },
    "rotation": {
      "x": 0,
      "y": 1.5707963267948966,
      "z": 0
    },
    "scale": {
      "x": 1,
      "y": 1,
      "z": 1
    }
  },
  {
    "assetId": "MinecartTrackStraight",
    "layerId": "layer_0",
    "position": {
      "x": 238.5,
      "y": 0.04,
      "z": 215.5
    },
    "rotation": {
      "x": 0,
      "y": 1.5707963267948966,
      "z": 0
    },
    "scale": {
      "x": 1,
      "y": 1,
      "z": 1
    }
  },
  {
    "assetId": "MinecartTrackTurn",
    "layerId": "layer_0",
    "position": {
      "x": 237.11023011337687,
      "y": 0.04,
      "z": 216.09584365633856
    },
    "rotation": {
      "x": 4.005934284325435e-32,
      "y": -3.3306690738754755e-16,
      "z": -3.8857805861880533e-16
    },
    "scale": {
      "x": 1,
      "y": 1,
      "z": 1
    }
  },
  {
    "assetId": "MinecartTrackStraight",
    "layerId": "layer_0",
    "position": {
      "x": 236.5,
      "y": 0.04,
      "z": 217.5
    },
    "rotation": {
      "x": 0,
      "y": 3.141592653589793,
      "z": 0
    },
    "scale": {
      "x": 1,
      "y": 1,
      "z": 1
    }
  },
  {
    "assetId": "stone wall",
    "layerId": "layer_0",
    "position": {
      "x": 241.89231024549255,
      "y": 0,
      "z": 216.93923820023832
    },
    "rotation": {
      "x": 0,
      "y": 1.5707963267948966,
      "z": 0
    },
    "scale": {
      "x": 0.95,
      "y": 1,
      "z": 1
    }
  },
  {
    "assetId": "stone wall",
    "layerId": "layer_0",
    "position": {
      "x": 241,
      "y": 0,
      "z": 218
    },
    "rotation": {
      "x": 0,
      "y": -2.2204460492503146e-16,
      "z": 0
    },
    "scale": {
      "x": 1,
      "y": 1,
      "z": 1
    }
  },
  {
    "assetId": "stone wall",
    "layerId": "layer_0",
    "position": {
      "x": 239.8872174685562,
      "y": 0,
      "z": 219
    },
    "rotation": {
      "x": 0,
      "y": -1.5707963267948966,
      "z": 0
    },
    "scale": {
      "x": 1,
      "y": 1,
      "z": 1
    }
  },
  {
    "assetId": "stone wall",
    "layerId": "layer_0",
    "position": {
      "x": 239.8872174685562,
      "y": 0,
      "z": 221
    },
    "rotation": {
      "x": 0,
      "y": 1.5707963267948963,
      "z": 0
    },
    "scale": {
      "x": 1,
      "y": 1,
      "z": 1
    }
  },
  {
    "assetId": "stone wall",
    "layerId": "layer_0",
    "position": {
      "x": 239,
      "y": 0.000964241923854601,
      "z": 222
    },
    "rotation": {
      "x": 0,
      "y": 3.1415926535897927,
      "z": 0
    },
    "scale": {
      "x": 1,
      "y": 1,
      "z": 1
    }
  },
  {
    "assetId": "stone wall",
    "layerId": "layer_0",
    "position": {
      "x": 241.89231024549255,
      "y": 0,
      "z": 214
    },
    "rotation": {
      "x": 0,
      "y": 1.5707963267948966,
      "z": 0
    },
    "scale": {
      "x": 1,
      "y": 1,
      "z": 1
    }
  },
  {
    "assetId": "stone wall",
    "layerId": "layer_0",
    "position": {
      "x": 241,
      "y": 0,
      "z": 213
    },
    "rotation": {
      "x": 0,
      "y": 3.141592653589793,
      "z": 0
    },
    "scale": {
      "x": 1,
      "y": 1,
      "z": 1
    }
  },
  {
    "assetId": "stone wall",
    "layerId": "layer_0",
    "position": {
      "x": 239,
      "y": 0,
      "z": 213
    },
    "rotation": {
      "x": 0,
      "y": 3.141592653589793,
      "z": 0
    },
    "scale": {
      "x": 1,
      "y": 1,
      "z": 1
    }
  },
  {
    "assetId": "stone wall",
    "layerId": "layer_0",
    "position": {
      "x": 237,
      "y": 0,
      "z": 213
    },
    "rotation": {
      "x": 0,
      "y": 3.141592653589793,
      "z": 0
    },
    "scale": {
      "x": 1,
      "y": 1,
      "z": 1
    }
  },
  {
    "assetId": "stone wall",
    "layerId": "layer_0",
    "position": {
      "x": 234.94757565543551,
      "y": 0,
      "z": 213
    },
    "rotation": {
      "x": 0,
      "y": 3.141592653589793,
      "z": 0
    },
    "scale": {
      "x": 1.05,
      "y": 1,
      "z": 1
    }
  },
  {
    "assetId": "stone wall",
    "layerId": "layer_0",
    "position": {
      "x": 237,
      "y": 0,
      "z": 222
    },
    "rotation": {
      "x": 0,
      "y": 3.1415926535897927,
      "z": 0
    },
    "scale": {
      "x": 1,
      "y": 1,
      "z": 1
    }
  },
  {
    "assetId": "stone wall",
    "layerId": "layer_0",
    "position": {
      "x": 235,
      "y": 0.00017265295494634395,
      "z": 222
    },
    "rotation": {
      "x": 0,
      "y": 3.1415926535897927,
      "z": 0
    },
    "scale": {
      "x": 1,
      "y": 1,
      "z": 1
    }
  },
  {
    "assetId": "stone wall",
    "layerId": "layer_0",
    "position": {
      "x": 234,
      "y": 0.00011146958703223295,
      "z": 218
    },
    "rotation": {
      "x": 0,
      "y": -1.5707963267948972,
      "z": 0
    },
    "scale": {
      "x": 1,
      "y": 1,
      "z": 1
    }
  },
  {
    "assetId": "stone wall",
    "layerId": "layer_0",
    "position": {
      "x": 234,
      "y": 0.001702361008948875,
      "z": 216
    },
    "rotation": {
      "x": 0,
      "y": -1.5707963267948972,
      "z": 0
    },
    "scale": {
      "x": 1,
      "y": 1,
      "z": 1
    }
  },
  {
    "assetId": "stone wall",
    "layerId": "layer_0",
    "position": {
      "x": 234,
      "y": 0.002743001482434539,
      "z": 214
    },
    "rotation": {
      "x": 0,
      "y": -1.5707963267948972,
      "z": 0
    },
    "scale": {
      "x": 1,
      "y": 1,
      "z": 1
    }
  },
  {
    "assetId": "stone wall door2",
    "layerId": "layer_0",
    "position": {
      "x": 234,
      "y": 0.0033188715208953288,
      "z": 220.54757357683465
    },
    "rotation": {
      "x": 0,
      "y": -1.5707963267948966,
      "z": 0
    },
    "scale": {
      "x": 1.5499999999999998,
      "y": 1,
      "z": 1
    }
  },
  {
    "assetId": "table1",
    "layerId": "layer_0",
    "position": {
      "x": 239.33344817054686,
      "y": 0,
      "z": 219.5
    },
    "rotation": {
      "x": 0,
      "y": 0,
      "z": 0
    },
    "scale": {
      "x": 0.5499999999999997,
      "y": 0.5499999999999997,
      "z": 0.5499999999999997
    }
  },
  {
    "assetId": "Crate1",
    "layerId": "layer_0",
    "position": {
      "x": 239.5,
      "y": 0,
      "z": 218.5
    },
    "rotation": {
      "x": 0,
      "y": 0,
      "z": 0
    },
    "scale": {
      "x": 0.7999999999999998,
      "y": 0.7999999999999998,
      "z": 0.7999999999999998
    }
  },
  {
    "assetId": "Crate1",
    "layerId": "layer_0",
    "position": {
      "x": 239.5,
      "y": 0,
      "z": 217.5
    },
    "rotation": {
      "x": 0,
      "y": 0,
      "z": 0
    },
    "scale": {
      "x": 0.7999999999999998,
      "y": 0.7999999999999998,
      "z": 0.7999999999999998
    }
  },
  {
    "assetId": "Crate1",
    "layerId": "layer_0",
    "position": {
      "x": 239.5,
      "y": 0.7199999809265135,
      "z": 217.5
    },
    "rotation": {
      "x": 0,
      "y": 0,
      "z": 0
    },
    "scale": {
      "x": 0.7999999999999998,
      "y": 0.7999999999999998,
      "z": 0.7999999999999998
    }
  },
  {
    "assetId": "Crate1",
    "layerId": "layer_0",
    "position": {
      "x": 240.5,
      "y": 0,
      "z": 217.5
    },
    "rotation": {
      "x": 0,
      "y": 0,
      "z": 0
    },
    "scale": {
      "x": 0.7999999999999998,
      "y": 0.7999999999999998,
      "z": 0.7999999999999998
    }
  },
  {
    "assetId": "Crate1",
    "layerId": "layer_0",
    "position": {
      "x": 241.39726109759937,
      "y": 0,
      "z": 213.5
    },
    "rotation": {
      "x": 0,
      "y": 0,
      "z": 0
    },
    "scale": {
      "x": 0.7999999999999998,
      "y": 0.7999999999999998,
      "z": 0.7999999999999998
    }
  },
  {
    "assetId": "Crate1",
    "layerId": "layer_0",
    "position": {
      "x": 241.36705897946786,
      "y": 0,
      "z": 214.5
    },
    "rotation": {
      "x": 0,
      "y": 0,
      "z": 0
    },
    "scale": {
      "x": 0.7999999999999998,
      "y": 0.7999999999999998,
      "z": 0.7999999999999998
    }
  },
  {
    "assetId": "Crate1",
    "layerId": "layer_0",
    "position": {
      "x": 241.5,
      "y": 0.6832003021240234,
      "z": 214.5
    },
    "rotation": {
      "x": 0,
      "y": 0,
      "z": 0
    },
    "scale": {
      "x": 0.7999999999999998,
      "y": 0.7999999999999998,
      "z": 0.7999999999999998
    }
  },
  {
    "assetId": "Crate1",
    "layerId": "layer_0",
    "position": {
      "x": 238.5,
      "y": 0,
      "z": 213.5
    },
    "rotation": {
      "x": 0,
      "y": 0,
      "z": 0
    },
    "scale": {
      "x": 0.7999999999999998,
      "y": 0.7999999999999998,
      "z": 0.7999999999999998
    }
  },
  {
    "assetId": "Crate1",
    "layerId": "layer_0",
    "position": {
      "x": 239.5,
      "y": 0,
      "z": 213.5
    },
    "rotation": {
      "x": 0,
      "y": 0,
      "z": 0
    },
    "scale": {
      "x": 0.7999999999999998,
      "y": 0.7999999999999998,
      "z": 0.7999999999999998
    }
  },
  {
    "assetId": "Crate1",
    "layerId": "layer_0",
    "position": {
      "x": 239.5,
      "y": 0.7199999809265135,
      "z": 213.5
    },
    "rotation": {
      "x": 0,
      "y": 0,
      "z": 0
    },
    "scale": {
      "x": 0.7999999999999998,
      "y": 0.7999999999999998,
      "z": 0.7999999999999998
    }
  },
  {
    "assetId": "castleTruedoor",
    "layerId": "layer_0",
    "position": {
      "x": 233.98703491134663,
      "y": 0.007922628455224385,
      "z": 220.54091789992032
    },
    "rotation": {
      "x": 0,
      "y": -1.5707963267948966,
      "z": 0
    },
    "scale": {
      "x": 1.5999999999999996,
      "y": 2.0999999999999996,
      "z": 1.5999999999999996
    },
    "defaultOpen": true
  },
  {
    "assetId": "Crate1",
    "layerId": "layer_0",
    "position": {
      "x": 237.5,
      "y": 1.907348645691087e-8,
      "z": 213.5
    },
    "rotation": {
      "x": 0,
      "y": 0,
      "z": 0
    },
    "scale": {
      "x": 0.7999999999999998,
      "y": 0.7999999999999998,
      "z": 0.7999999999999998
    }
  },
  {
    "assetId": "Crate1",
    "layerId": "layer_0",
    "position": {
      "x": 234.5,
      "y": 0,
      "z": 217.5
    },
    "rotation": {
      "x": 0,
      "y": 0,
      "z": 0
    },
    "scale": {
      "x": 0.7999999999999998,
      "y": 0.7999999999999998,
      "z": 0.7999999999999998
    }
  },
  {
    "assetId": "Crate1",
    "layerId": "layer_0",
    "position": {
      "x": 234.5,
      "y": 0.7199999809265135,
      "z": 217.5
    },
    "rotation": {
      "x": 0,
      "y": 0,
      "z": 0
    },
    "scale": {
      "x": 0.7999999999999998,
      "y": 0.7999999999999998,
      "z": 0.7999999999999998
    }
  },
  {
    "assetId": "Crate1",
    "layerId": "layer_0",
    "position": {
      "x": 234.5,
      "y": 0,
      "z": 216.5
    },
    "rotation": {
      "x": 0,
      "y": 0,
      "z": 0
    },
    "scale": {
      "x": 0.7999999999999998,
      "y": 0.7999999999999998,
      "z": 0.7999999999999998
    }
  },
  {
    "assetId": "Crate1",
    "layerId": "layer_0",
    "position": {
      "x": 234.5,
      "y": 0.7199999809265135,
      "z": 216.5
    },
    "rotation": {
      "x": 0,
      "y": 0,
      "z": 0
    },
    "scale": {
      "x": 0.7999999999999998,
      "y": 0.7999999999999998,
      "z": 0.7999999999999998
    }
  },
  {
    "assetId": "Crate1",
    "layerId": "layer_0",
    "position": {
      "x": 234.5,
      "y": 0,
      "z": 215.5
    },
    "rotation": {
      "x": 0,
      "y": 0,
      "z": 0
    },
    "scale": {
      "x": 0.7999999999999998,
      "y": 0.7999999999999998,
      "z": 0.7999999999999998
    }
  },
  {
    "assetId": "Sack2",
    "layerId": "layer_0",
    "position": {
      "x": 234.5,
      "y": 0,
      "z": 214.5
    },
    "rotation": {
      "x": 0.26179938779914935,
      "y": -1.308996938995747,
      "z": 0
    },
    "scale": {
      "x": 2.799999999999999,
      "y": 2.799999999999999,
      "z": 2.799999999999999
    }
  },
  {
    "assetId": "Sack1",
    "layerId": "layer_0",
    "position": {
      "x": 234.5,
      "y": 0.007223560920789383,
      "z": 218.5
    },
    "rotation": {
      "x": -0.6457718232379015,
      "y": -1.543376357425981e-32,
      "z": 1.110223024625157e-16
    },
    "scale": {
      "x": 2.949999999999999,
      "y": 2.949999999999999,
      "z": 2.949999999999999
    }
  },
  {
    "assetId": "Sack2",
    "layerId": "layer_0",
    "position": {
      "x": 236.5,
      "y": 0,
      "z": 213.5
    },
    "rotation": {
      "x": -0.7971464456861586,
      "y": -1.1135740535374707,
      "z": -0.1423677326617955
    },
    "scale": {
      "x": 2.799999999999999,
      "y": 2.799999999999999,
      "z": 2.799999999999999
    }
  },
  {
    "assetId": "Minecart",
    "layerId": "layer_0",
    "position": {
      "x": 236.5,
      "y": 0.12,
      "z": 217.5
    },
    "rotation": {
      "x": 0,
      "y": 0,
      "z": 0
    },
    "scale": {
      "x": 1.1500000000000001,
      "y": 1.1500000000000001,
      "z": 1.1500000000000001
    }
  },
  {
    "assetId": "MinecartTrackStop",
    "layerId": "layer_0",
    "position": {
      "x": 236.5,
      "y": 0,
      "z": 218.41801828354934
    },
    "rotation": {
      "x": 0,
      "y": 0,
      "z": 0
    },
    "scale": {
      "x": 0.95,
      "y": 0.95,
      "z": 0.95
    }
  },
  {
    "assetId": "stone slabs",
    "layerId": "layer_0",
    "position": {
      "x": 234.6258678412179,
      "y": 2.720286360205927,
      "z": 222
    },
    "rotation": {
      "x": 0,
      "y": 0,
      "z": 0
    },
    "scale": {
      "x": 0.7999999999999998,
      "y": 0.8999999999999999,
      "z": 0.4499999999999996
    }
  },
  {
    "assetId": "stone slabs",
    "layerId": "layer_0",
    "position": {
      "x": 236.08890840562145,
      "y": 2.720286360205927,
      "z": 222
    },
    "rotation": {
      "x": 0,
      "y": 0,
      "z": 0
    },
    "scale": {
      "x": 0.7999999999999998,
      "y": 0.8999999999999999,
      "z": 0.4499999999999996
    }
  },
  {
    "assetId": "stone slabs",
    "layerId": "layer_0",
    "position": {
      "x": 237.551948970025,
      "y": 2.720286360205927,
      "z": 222
    },
    "rotation": {
      "x": 0,
      "y": 0,
      "z": 0
    },
    "scale": {
      "x": 0.7999999999999998,
      "y": 0.8999999999999999,
      "z": 0.4499999999999996
    }
  },
  {
    "assetId": "stone slabs",
    "layerId": "layer_0",
    "position": {
      "x": 239.06011976402374,
      "y": 2.720286360205927,
      "z": 222
    },
    "rotation": {
      "x": 0,
      "y": 0,
      "z": 0
    },
    "scale": {
      "x": 0.8499999999999999,
      "y": 0.8999999999999999,
      "z": 0.4499999999999996
    }
  },
  {
    "assetId": "stone slabs",
    "layerId": "layer_0",
    "position": {
      "x": 239.899661577339,
      "y": 2.720286360205927,
      "z": 221.32477330583168
    },
    "rotation": {
      "x": 6.162975822039155e-33,
      "y": 1.5707963267948963,
      "z": 1.1102230246251568e-16
    },
    "scale": {
      "x": 0.8499999999999999,
      "y": 0.8999999999999999,
      "z": 0.4499999999999996
    }
  },
  {
    "assetId": "stone slabs",
    "layerId": "layer_0",
    "position": {
      "x": 239.899661577339,
      "y": 2.720286360205927,
      "z": 219.77140124203055
    },
    "rotation": {
      "x": 6.162975822039155e-33,
      "y": 1.5707963267948963,
      "z": 1.1102230246251568e-16
    },
    "scale": {
      "x": 0.8499999999999999,
      "y": 0.8999999999999999,
      "z": 0.4499999999999996
    }
  },
  {
    "assetId": "stone slabs",
    "layerId": "layer_0",
    "position": {
      "x": 241.9038602992375,
      "y": 2.720286360205927,
      "z": 217.26402952667098
    },
    "rotation": {
      "x": 6.162975822039155e-33,
      "y": 1.5707963267948963,
      "z": 1.1102230246251568e-16
    },
    "scale": {
      "x": 0.7,
      "y": 0.8999999999999999,
      "z": 0.4499999999999996
    }
  },
  {
    "assetId": "stone slabs",
    "layerId": "layer_0",
    "position": {
      "x": 240.45105049909395,
      "y": 2.720286360205927,
      "z": 218.00733707235946
    },
    "rotation": {
      "x": -5.887846720064147e-17,
      "y": 3.1415926535897927,
      "z": 9.813077866773603e-17
    },
    "scale": {
      "x": 0.7,
      "y": 0.8999999999999999,
      "z": 0.4499999999999996
    }
  },
  {
    "assetId": "stone slabs",
    "layerId": "layer_0",
    "position": {
      "x": 241.54926574864126,
      "y": 2.720286360205927,
      "z": 218.00733707235946
    },
    "rotation": {
      "x": -5.887846720064147e-17,
      "y": 3.1415926535897927,
      "z": 9.813077866773603e-17
    },
    "scale": {
      "x": 0.49999999999999983,
      "y": 0.8999999999999999,
      "z": 0.4499999999999996
    }
  },
  {
    "assetId": "stone slabs",
    "layerId": "layer_0",
    "position": {
      "x": 239.90092393546033,
      "y": 2.720286360205927,
      "z": 218.5373839204629
    },
    "rotation": {
      "x": 6.162975822039155e-33,
      "y": 1.5707963267948963,
      "z": 1.1102230246251568e-16
    },
    "scale": {
      "x": 0.4999999999999998,
      "y": 0.8999999999999999,
      "z": 0.4499999999999996
    }
  },
  {
    "assetId": "stone slabs",
    "layerId": "layer_0",
    "position": {
      "x": 241.9038602992375,
      "y": 2.720286360205927,
      "z": 215.99050399461265
    },
    "rotation": {
      "x": 6.162975822039155e-33,
      "y": 1.5707963267948963,
      "z": 1.1102230246251568e-16
    },
    "scale": {
      "x": 0.7,
      "y": 0.8999999999999999,
      "z": 0.4499999999999996
    }
  },
  {
    "assetId": "stone slabs",
    "layerId": "layer_0",
    "position": {
      "x": 241.9038602992375,
      "y": 2.720286360205927,
      "z": 214.71679276317553
    },
    "rotation": {
      "x": 6.162975822039155e-33,
      "y": 1.5707963267948963,
      "z": 1.1102230246251568e-16
    },
    "scale": {
      "x": 0.7,
      "y": 0.8999999999999999,
      "z": 0.4499999999999996
    }
  },
  {
    "assetId": "stone slabs",
    "layerId": "layer_0",
    "position": {
      "x": 241.9038602992375,
      "y": 2.720286360205927,
      "z": 213.48175330710754
    },
    "rotation": {
      "x": 6.162975822039155e-33,
      "y": 1.5707963267948963,
      "z": 1.1102230246251568e-16
    },
    "scale": {
      "x": 0.6499999999999999,
      "y": 0.8999999999999999,
      "z": 0.4499999999999996
    }
  },
  {
    "assetId": "stone slabs",
    "layerId": "layer_0",
    "position": {
      "x": 234.6258678412179,
      "y": 2.720286360205927,
      "z": 212.9895622492177
    },
    "rotation": {
      "x": 0,
      "y": 0,
      "z": 0
    },
    "scale": {
      "x": 0.7999999999999998,
      "y": 0.8999999999999999,
      "z": 0.4499999999999996
    }
  },
  {
    "assetId": "stone slabs",
    "layerId": "layer_0",
    "position": {
      "x": 236.08890840562145,
      "y": 2.720286360205927,
      "z": 212.9895622492177
    },
    "rotation": {
      "x": 0,
      "y": 0,
      "z": 0
    },
    "scale": {
      "x": 0.7999999999999998,
      "y": 0.8999999999999999,
      "z": 0.4499999999999996
    }
  },
  {
    "assetId": "stone slabs",
    "layerId": "layer_0",
    "position": {
      "x": 237.551948970025,
      "y": 2.720286360205927,
      "z": 212.9895622492177
    },
    "rotation": {
      "x": 0,
      "y": 0,
      "z": 0
    },
    "scale": {
      "x": 0.7999999999999998,
      "y": 0.8999999999999999,
      "z": 0.4499999999999996
    }
  },
  {
    "assetId": "stone slabs",
    "layerId": "layer_0",
    "position": {
      "x": 239.2279514182074,
      "y": 2.720286360205927,
      "z": 212.9895622492177
    },
    "rotation": {
      "x": 0,
      "y": 0,
      "z": 0
    },
    "scale": {
      "x": 1.05,
      "y": 0.8999999999999999,
      "z": 0.4499999999999996
    }
  },
  {
    "assetId": "stone slabs",
    "layerId": "layer_0",
    "position": {
      "x": 240.9891607028042,
      "y": 2.720286360205927,
      "z": 212.99508387227206
    },
    "rotation": {
      "x": 0,
      "y": 0,
      "z": 0
    },
    "scale": {
      "x": 0.8999999999999999,
      "y": 0.8999999999999999,
      "z": 0.4499999999999996
    }
  },
  {
    "assetId": "stone slabs",
    "layerId": "layer_0",
    "position": {
      "x": 234,
      "y": 2.720286360205927,
      "z": 221.16926755961103
    },
    "rotation": {
      "x": 0,
      "y": 1.5707963267948966,
      "z": 0
    },
    "scale": {
      "x": 0.7999999999999998,
      "y": 0.8999999999999999,
      "z": 0.4499999999999996
    }
  },
  {
    "assetId": "stone slabs",
    "layerId": "layer_0",
    "position": {
      "x": 234,
      "y": 2.720286360205927,
      "z": 219.70038022221462
    },
    "rotation": {
      "x": 0,
      "y": 1.5707963267948966,
      "z": 0
    },
    "scale": {
      "x": 0.7999999999999998,
      "y": 0.8999999999999999,
      "z": 0.4499999999999996
    }
  },
  {
    "assetId": "stone slabs",
    "layerId": "layer_0",
    "position": {
      "x": 234,
      "y": 2.720286360205927,
      "z": 218.24001635622562
    },
    "rotation": {
      "x": 0,
      "y": 1.5707963267948966,
      "z": 0
    },
    "scale": {
      "x": 0.7999999999999998,
      "y": 0.8999999999999999,
      "z": 0.4499999999999996
    }
  },
  {
    "assetId": "stone slabs",
    "layerId": "layer_0",
    "position": {
      "x": 234,
      "y": 2.720286360205927,
      "z": 216.7735591763815
    },
    "rotation": {
      "x": 0,
      "y": 1.5707963267948966,
      "z": 0
    },
    "scale": {
      "x": 0.7999999999999998,
      "y": 0.8999999999999999,
      "z": 0.4499999999999996
    }
  },
  {
    "assetId": "stone slabs",
    "layerId": "layer_0",
    "position": {
      "x": 234,
      "y": 2.720286360205927,
      "z": 215.30837115209522
    },
    "rotation": {
      "x": 0,
      "y": 1.5707963267948966,
      "z": 0
    },
    "scale": {
      "x": 0.7999999999999998,
      "y": 0.8999999999999999,
      "z": 0.4499999999999996
    }
  },
  {
    "assetId": "stone slabs",
    "layerId": "layer_0",
    "position": {
      "x": 234,
      "y": 2.720286360205927,
      "z": 213.85185906509565
    },
    "rotation": {
      "x": 0,
      "y": 1.5707963267948966,
      "z": 0
    },
    "scale": {
      "x": 0.8499999999999999,
      "y": 0.8999999999999999,
      "z": 0.4499999999999996
    }
  },
  {
    "assetId": "Tanning Rack",
    "layerId": "layer_0",
    "position": {
      "x": 229.5,
      "y": 0.2076680255994915,
      "z": 217.5
    },
    "rotation": {
      "x": 0,
      "y": -1.5707963267948966,
      "z": 0
    },
    "scale": {
      "x": 1.15,
      "y": 1.15,
      "z": 1.15
    }
  },
  {
    "assetId": "PalmTree",
    "layerId": "layer_0",
    "position": {
      "x": 243.954614743618,
      "y": 0.1100756168763406,
      "z": 213.11857476548948
    },
    "rotation": {
      "x": 0,
      "y": 1.308996938995747,
      "z": 0
    },
    "scale": {
      "x": 1,
      "y": 1,
      "z": 1
    }
  },
  {
    "assetId": "PalmTree",
    "layerId": "layer_0",
    "position": {
      "x": 252.07257382349601,
      "y": 0,
      "z": 219.62959094719923
    },
    "rotation": {
      "x": 0,
      "y": 3.141592653589793,
      "z": 0
    },
    "scale": {
      "x": 0.9499999999999997,
      "y": 1.3999999999999997,
      "z": 1.0499999999999998
    }
  },
  {
    "assetId": "Barrel",
    "layerId": "layer_0",
    "position": {
      "x": 234.5,
      "y": 0,
      "z": 222.5
    },
    "rotation": {
      "x": 0,
      "y": 0,
      "z": 0
    },
    "scale": {
      "x": 1,
      "y": 1,
      "z": 1
    }
  },
  {
    "assetId": "Barrel",
    "layerId": "layer_0",
    "position": {
      "x": 235.5,
      "y": 0,
      "z": 222.5
    },
    "rotation": {
      "x": 0,
      "y": 0,
      "z": 0
    },
    "scale": {
      "x": 1,
      "y": 1,
      "z": 1
    }
  },
  {
    "assetId": "Barrel",
    "layerId": "layer_0",
    "position": {
      "x": 235.5,
      "y": 0,
      "z": 213.5
    },
    "rotation": {
      "x": 0,
      "y": 0,
      "z": 0
    },
    "scale": {
      "x": 1,
      "y": 1,
      "z": 1
    }
  },
  {
    "assetId": "Barrel",
    "layerId": "layer_0",
    "position": {
      "x": 234.5,
      "y": 0.0011573180726469844,
      "z": 221.5
    },
    "rotation": {
      "x": 0,
      "y": 0,
      "z": 0
    },
    "scale": {
      "x": 1,
      "y": 1,
      "z": 1
    }
  },
  {
    "assetId": "tier 2 chest",
    "layerId": "layer_0",
    "position": {
      "x": 247.5,
      "y": 2.82787964817757,
      "z": 217.5
    },
    "rotation": {
      "x": 0,
      "y": 0,
      "z": 0
    },
    "scale": {
      "x": 1.1,
      "y": 1.1,
      "z": 1.1
    }
  },
  {
    "assetId": "tier 2 chest",
    "layerId": "layer_0",
    "position": {
      "x": 246.5,
      "y": 2.82787964817757,
      "z": 217.5
    },
    "rotation": {
      "x": 0,
      "y": 0,
      "z": 0
    },
    "scale": {
      "x": 1.1,
      "y": 1.1,
      "z": 1.1
    }
  }
]